[
  {
    "name": "Lakeside",
    "image": "lakeside.png",
    "gamemode": "koth",
    "status4v5": "Experimenting",
    "status6v6": "Experimenting",
    "statusPro": "Anchor",
    "statusHL": "Anchor",
    "reason": ""
  },
  {
    "name": "Skyfall",
    "image": "skyfall.png",
    "gamemode": "koth",
    "status4v5": "Vaulted",
    "status6v6": "Vaulted",
    "statusPro": "Vaulted",
    "statusHL": "Vaulted",
    "reason": ""
  },
  {
    "name": "Orange",
    "image": "koth_orange.png",
    "gamemode": "koth",
    "status4v5": "Vaulted",
    "status6v6": "Vaulted",
    "statusPro": "Vaulted",
    "statusHL": "Vaulted",
    "reason": ""
  },
  {
    "name": "Warmtic",
    "image": "warmtic.png",
    "gamemode": "koth",
    "status4v5": "Anchor",
    "status6v6": "Anchor",
    "statusPro": "In Rotation",
    "statusHL": "In Rotation",
    "reason": ""
  },
  {
    "name": "Sawmill",
    "image": "sawmill.png",
    "gamemode": "koth",
    "status4v5": "Vaulted",
    "status6v6": "Vaulted",
    "statusPro": "Experimenting",
    "statusHL": "Experimenting",
    "reason": ""
  },
  {
    "name": "Rooftop (Old)",
    "image": "rooftop_old.png",
    "gamemode": "koth",
    "status4v5": "Vaulted",
    "status6v6": "Vaulted",
    "statusPro": "Vaulted",
    "statusHL": "Vaulted",
    "reason": ""
  },
  {
    "name": "Rooftops (New)",
    "image": "rooftops_new.png",
    "gamemode": "koth",
    "status4v5": "Experimenting",
    "status6v6": "Experimenting",
    "statusPro": "In Rotation",
    "statusHL": "In Rotation",
    "reason": ""
  },
  {
    "name": "Product",
    "image": "product.png",
    "gamemode": "koth",
    "status4v5": "Anchor",
    "status6v6": "Anchor",
    "statusPro": "Anchor",
    "statusHL": "Anchor",
    "reason": ""
  },
  {
    "name": "Harvest",
    "image": "harvest.png",
    "gamemode": "koth",
    "status4v5": "Vaulted",
    "status6v6": "Vaulted",
    "statusPro": "Experimenting",
    "statusHL": "Experimenting",
    "reason": ""
  },
  {
    "name": "Harvest Alpine",
    "image": "harvest_alpine.png",
    "gamemode": "koth",
    "status4v5": "Vaulted",
    "status6v6": "Vaulted",
    "statusPro": "Out of rotation",
    "statusHL": "Out of rotation",
    "reason": "Summer"
  },
  {
    "name": "Harvest Winter",
    "image": "harvest_winter.png",
    "gamemode": "koth",
    "status4v5": "Vaulted",
    "status6v6": "Vaulted",
    "statusPro": "Out of rotation",
    "statusHL": "Out of rotation",
    "reason": "Christmas"
  },
  {
    "name": "Reap",
    "image": "reap.png",
    "gamemode": "koth",
    "status4v5": "Vaulted",
    "status6v6": "Vaulted",
    "statusPro": "Vaulted",
    "statusHL": "Vaulted",
    "reason": "Crumpkins"
  },
  {
    "name": "Defrost",
    "image": "defrost.png",
    "gamemode": "koth",
    "status4v5": "Vaulted",
    "status6v6": "Vaulted",
    "statusPro": "Vaulted",
    "statusHL": "Vaulted",
    "reason": ""
  },
  {
    "name": "Snoduct",
    "image": "snoduct.png",
    "gamemode": "koth",
    "status4v5": "Out of rotation",
    "status6v6": "Out of rotation",
    "statusPro": "Out of rotation",
    "statusHL": "Out of rotation",
    "reason": "Christmas"
  },
  {
    "name": "Arctic",
    "image": "arctic.png",
    "gamemode": "koth",
    "status4v5": "Out of rotation",
    "status6v6": "Out of rotation",
    "statusPro": "Out of rotation",
    "statusHL": "Out of rotation",
    "reason": "Christmas"
  },
  {
    "name": "Bagel",
    "image": "bagel.png",
    "gamemode": "koth",
    "status4v5": "Anchor",
    "status6v6": "Anchor",
    "statusPro": "Experimenting",
    "statusHL": "Experimenting",
    "reason": ""
  },
  {
    "name": "Argyle",
    "image": "argyle.png",
    "gamemode": "koth",
    "status4v5": "Experimenting",
    "status6v6": "Experimenting",
    "statusPro": "Experimenting",
    "statusHL": "Experimenting",
    "reason": ""
  },
  {
    "name": "Citrus",
    "image": "citrus.png",
    "gamemode": "koth",
    "status4v5": "Experimenting",
    "status6v6": "Experimenting",
    "statusPro": "Experimenting",
    "statusHL": "Experimenting",
    "reason": ""
  },
  {
    "name": "Petra",
    "image": "petra.png",
    "gamemode": "koth",
    "status4v5": "Experimenting",
    "status6v6": "Experimenting",
    "statusPro": "Experimenting",
    "statusHL": "Experimenting",
    "reason": ""
  },
  {
    "name": "Power Plant",
    "image": "power_plant.png",
    "gamemode": "koth",
    "status4v5": "Experimenting",
    "status6v6": "Experimenting",
    "statusPro": "Experimenting",
    "statusHL": "Experimenting",
    "reason": ""
  },
  {
    "name": "Shiverift",
    "image": "shiverift.png",
    "gamemode": "koth",
    "status4v5": "Experimenting",
    "status6v6": "Experimenting",
    "statusPro": "Experimenting",
    "statusHL": "Experimenting",
    "reason": ""
  },
  {
    "name": "Smog",
    "image": "smog.png",
    "gamemode": "koth",
    "status4v5": "Vaulted",
    "status6v6": "Vaulted",
    "statusPro": "Vaulted",
    "statusHL": "Vaulted",
    "reason": ""
  },
  {
    "name": "Yellowvalley",
    "image": "ad_yellowvalley.png",
    "gamemode": "ad",
    "status4v5": "Vaulted",
    "status6v6": "Vaulted",
    "statusPro": "Experimenting",
    "statusHL": "Experimenting",
    "reason": ""
  },
  {
    "name": "Cliffhanger",
    "image": "cliffhanger.png",
    "gamemode": "ad",
    "status4v5": "Vaulted",
    "status6v6": "Vaulted",
    "statusPro": "Experimenting",
    "statusHL": "Experimenting",
    "reason": ""
  },
  {
    "name": "Isolated",
    "image": "isolated.png",
    "gamemode": "ad",
    "status4v5": "Vaulted",
    "status6v6": "Vaulted",
    "statusPro": "Experimenting",
    "statusHL": "Experimenting",
    "reason": ""
  },
  {
    "name": "Solarpower",
    "image": "solarpower.png",
    "gamemode": "ad",
    "status4v5": "Vaulted",
    "status6v6": "Vaulted",
    "statusPro": "Vaulted",
    "statusHL": "Vaulted",
    "reason": ""
  },
  {
    "name": "Tropical",
    "image": "tropical.png",
    "gamemode": "ad",
    "status4v5": "Vaulted",
    "status6v6": "Vaulted",
    "statusPro": "Experimenting",
    "statusHL": "Experimenting",
    "reason": ""
  },
  {
    "name": "Gorge",
    "image": "gorge.png",
    "gamemode": "ad",
    "status4v5": "Vaulted",
    "status6v6": "Vaulted",
    "statusPro": "Experimenting",
    "statusHL": "Experimenting",
    "reason": ""
  },
  {
    "name": "Liana",
    "image": "liana.png",
    "gamemode": "ad",
    "status4v5": "Vaulted",
    "status6v6": "Vaulted",
    "statusPro": "Experimenting",
    "statusHL": "Experimenting",
    "reason": ""
  },
  {
    "name": "Calamity (New)",
    "image": "calamity.png",
    "gamemode": "pl",
    "status4v5": "Vaulted",
    "status6v6": "Vaulted",
    "statusPro": "Experimenting",
    "statusHL": "Experimenting",
    "reason": ""
  },
  {
    "name": "Boundary",
    "image": "boundary.png",
    "gamemode": "pl",
    "status4v5": "Vaulted",
    "status6v6": "Vaulted",
    "statusPro": "Vaulted",
    "statusHL": "Vaulted",
    "reason": ""
  },
  {
    "name": "Upward",
    "image": "upward.png",
    "gamemode": "pl",
    "status4v5": "Vaulted",
    "status6v6": "Vaulted",
    "statusPro": "Anchor",
    "statusHL": "Anchor",
    "reason": ""
  },
  {
    "name": "Badwater",
    "image": "badwater.png",
    "gamemode": "pl",
    "status4v5": "Vaulted",
    "status6v6": "Vaulted",
    "statusPro": "Anchor",
    "statusHL": "Anchor",
    "reason": ""
  },
  {
    "name": "Blastport",
    "image": "blastport.png",
    "gamemode": "pl",
    "status4v5": "Vaulted",
    "status6v6": "Vaulted",
    "statusPro": "Out of rotation",
    "statusHL": "Out of rotation",
    "reason": ""
  },
  {
    "name": "Banana Shore",
    "image": "banana_shore.png",
    "gamemode": "pl",
    "status4v5": "Vaulted",
    "status6v6": "Vaulted",
    "statusPro": "Out of rotation",
    "statusHL": "Out of rotation",
    "reason": ""
  },
  {
    "name": "Manufacturing",
    "image": "manufacturing.png",
    "gamemode": "pl",
    "status4v5": "Vaulted",
    "status6v6": "Vaulted",
    "statusPro": "Experimenting",
    "statusHL": "Experimenting",
    "reason": ""
  },
  {
    "name": "Taiga",
    "image": "taiga.png",
    "gamemode": "pl",
    "status4v5": "Vaulted",
    "status6v6": "Vaulted",
    "statusPro": "Vaulted",
    "statusHL": "Vaulted",
    "reason": ""
  },
  {
    "name": "Frost",
    "image": "cp_frost.png",
    "gamemode": "cp",
    "status4v5": "Experimenting",
    "status6v6": "Experimenting",
    "statusPro": "Experimenting",
    "statusHL": "Experimenting",
    "reason": ""
  },
  {
    "name": "Citrus",
    "image": "cp_citrus.png",
    "gamemode": "cp",
    "status4v5": "Experimenting",
    "status6v6": "Experimenting",
    "statusPro": "Experimenting",
    "statusHL": "Experimenting",
    "reason": ""
  },
  {
    "name": "3CP Yellowvalley",
    "image": "3cp_yellowvalley.png",
    "gamemode": "cp",
    "status4v5": "Experimenting",
    "status6v6": "Experimenting",
    "statusPro": "Experimenting",
    "statusHL": "Experimenting",
    "reason": ""
  },
  {
    "name": "Undergrove",
    "image": "undergrove.png",
    "gamemode": "cp",
    "status4v5": "Experimenting",
    "status6v6": "Experimenting",
    "statusPro": "Experimenting",
    "statusHL": "Experimenting",
    "reason": ""
  },
  {
    "name": "Staredawn",
    "image": "staredawn.png",
    "gamemode": "cp",
    "status4v5": "Experimenting",
    "status6v6": "Experimenting",
    "statusPro": "Experimenting",
    "statusHL": "Experimenting",
    "reason": ""
  },
  {
    "name": "Dam",
    "image": "dam.png",
    "gamemode": "ctf",
    "status4v5": "Vaulted",
    "status6v6": "Vaulted",
    "statusPro": "Vaulted",
    "statusHL": "Vaulted",
    "reason": ""
  },
  {
    "name": "Doublefort",
    "image": "doublefort.png",
    "gamemode": "ctf",
    "status4v5": "Vaulted",
    "status6v6": "Vaulted",
    "statusPro": "Experimenting",
    "statusHL": "Experimenting",
    "reason": ""
  },
  {
    "name": "Mach",
    "image": "mach.png",
    "gamemode": "ctf",
    "status4v5": "Vaulted",
    "status6v6": "Vaulted",
    "statusPro": "Vaulted",
    "statusHL": "Vaulted",
    "reason": ""
  },
  {
    "name": "Rig",
    "image": "rig.png",
    "gamemode": "ctf",
    "status4v5": "Vaulted",
    "status6v6": "Vaulted",
    "statusPro": "Vaulted",
    "statusHL": "Vaulted",
    "reason": ""
  },
  {
    "name": "Runnel",
    "image": "runnel.png",
    "gamemode": "ctf",
    "status4v5": "Vaulted",
    "status6v6": "Vaulted",
    "statusPro": "Experimenting",
    "statusHL": "Experimenting",
    "reason": ""
  },
  {
    "name": "Turbine",
    "image": "turbine_pro.png",
    "gamemode": "ctf",
    "status4v5": "Vaulted",
    "status6v6": "Vaulted",
    "statusPro": "Experimenting",
    "statusHL": "Experimenting",
    "reason": ""
  },
  {
    "name": "Warmlane",
    "image": "warmlane.png",
    "gamemode": "ctf",
    "status4v5": "Vaulted",
    "status6v6": "Vaulted",
    "statusPro": "Experimenting",
    "statusHL": "Experimenting",
    "reason": ""
  },
  {
    "name": "Whitelane",
    "image": "whitelane.png",
    "gamemode": "ctf",
    "status4v5": "Vaulted",
    "status6v6": "Vaulted",
    "statusPro": "Vaulted",
    "statusHL": "Vaulted",
    "reason": "Christmas"
  }
]
